[
  {
    "prediction_time": "2026-03-10T16:51:55Z",
    "check_time": "2026-03-10T17:35:00Z",
    "short_term_signal": "BEARISH",
    "short_term_correct": false,
    "confidence_at_prediction": 75,
    "ticker_results": [
      {
        "ticker": "SPY",
        "predicted_direction": "BEARISH",
        "actual_direction": "BULLISH",
        "predicted_price": 678.5,
        "actual_price": 682.02,
        "price_error_pct": 0.519,
        "correct": false
      },
      {
        "ticker": "MSFT",
        "predicted_direction": "BEARISH",
        "actual_direction": "BEARISH",
        "predicted_price": 403.0,
        "actual_price": 405.38,
        "price_error_pct": 0.591,
        "correct": true
      },
      {
        "ticker": "IWM",
        "predicted_direction": "NEUTRAL",
        "actual_direction": "BULLISH",
        "predicted_price": 256.0,
        "actual_price": 257.11,
        "price_error_pct": 0.434,
        "correct": false
      }
    ],
    "overall_accuracy": 0.333
  },
  {
    "prediction_time": "2026-03-10T17:40:01Z",
    "check_time": "2026-03-10T19:35:01Z",
    "short_term_signal": "BEARISH",
    "short_term_correct": true,
    "confidence_at_prediction": 65,
    "ticker_results": [
      {
        "ticker": "SPY",
        "predicted_direction": "BEARISH",
        "actual_direction": "BEARISH",
        "predicted_price": 679.5,
        "actual_price": 677.03,
        "price_error_pct": 0.364,
        "correct": true
      },
      {
        "ticker": "MSFT",
        "predicted_direction": "BEARISH",
        "actual_direction": "BEARISH",
        "predicted_price": 403.0,
        "actual_price": 404.55,
        "price_error_pct": 0.385,
        "correct": true
      },
      {
        "ticker": "IWM",
        "predicted_direction": "NEUTRAL",
        "actual_direction": "BEARISH",
        "predicted_price": 256.5,
        "actual_price": 253.4,
        "price_error_pct": 1.209,
        "correct": false
      },
      {
        "ticker": "NVDA",
        "predicted_direction": "NEUTRAL",
        "actual_direction": "BEARISH",
        "predicted_price": 185.0,
        "actual_price": 184.16,
        "price_error_pct": 0.454,
        "correct": false
      }
    ],
    "overall_accuracy": 0.5
  },
  {
    "prediction_time": "2026-03-10T19:40:01Z",
    "check_time": "2026-03-10T21:35:01Z",
    "short_term_signal": "BEARISH",
    "short_term_correct": false,
    "confidence_at_prediction": 70,
    "ticker_results": [
      {
        "ticker": "SPY",
        "predicted_direction": "BEARISH",
        "actual_direction": "NEUTRAL",
        "predicted_price": 675.5,
        "actual_price": 677.18,
        "price_error_pct": 0.249,
        "correct": false
      },
      {
        "ticker": "MSFT",
        "predicted_direction": "BEARISH",
        "actual_direction": "BULLISH",
        "predicted_price": 402.0,
        "actual_price": 405.76,
        "price_error_pct": 0.935,
        "correct": false
      },
      {
        "ticker": "IWM",
        "predicted_direction": "NEUTRAL",
        "actual_direction": "BEARISH",
        "predicted_price": 253.5,
        "actual_price": 253.36,
        "price_error_pct": 0.055,
        "correct": false
      },
      {
        "ticker": "NVDA",
        "predicted_direction": "NEUTRAL",
        "actual_direction": "BULLISH",
        "predicted_price": 184.0,
        "actual_price": 184.77,
        "price_error_pct": 0.418,
        "correct": false
      }
    ],
    "overall_accuracy": 0.0
  },
  {
    "prediction_time": "2026-03-11T13:40:01Z",
    "check_time": "2026-03-11T15:35:00Z",
    "timeframe": "intraday",
    "signal": "BEARISH",
    "signal_correct": false,
    "confidence_at_prediction": 75,
    "ticker_results": [
      {
        "ticker": "TSLA",
        "predicted_direction": "BEARISH",
        "actual_direction": "NEUTRAL",
        "predicted_price": 405.0,
        "actual_price": 408.38,
        "price_error_pct": 0.835,
        "correct": false
      },
      {
        "ticker": "IWM",
        "predicted_direction": "BEARISH",
        "actual_direction": "BEARISH",
        "predicted_price": 251.0,
        "actual_price": 251.73,
        "price_error_pct": 0.291,
        "correct": true
      },
      {
        "ticker": "NVDA",
        "predicted_direction": "NEUTRAL",
        "actual_direction": "BEARISH",
        "predicted_price": 185.5,
        "actual_price": 185.48,
        "price_error_pct": 0.011,
        "correct": false
      }
    ],
    "overall_accuracy": 0.333
  },
  {
    "prediction_time": "2026-03-11T15:40:00Z",
    "check_time": "2026-03-11T17:32:00Z",
    "timeframe": "intraday",
    "trigger_type": "manual",
    "signal": "BEARISH",
    "signal_correct": false,
    "confidence_at_prediction": 65,
    "ticker_results": [
      {
        "ticker": "IWM",
        "predicted_direction": "BEARISH",
        "actual_direction": "BULLISH",
        "predicted_price": 250.4,
        "actual_price": 252.23,
        "price_error_pct": 0.731,
        "correct": false
      },
      {
        "ticker": "TSLA",
        "predicted_direction": "NEUTRAL",
        "actual_direction": "BULLISH",
        "predicted_price": 406.0,
        "actual_price": 408.14,
        "price_error_pct": 0.527,
        "correct": false
      },
      {
        "ticker": "XLE",
        "predicted_direction": "BULLISH",
        "actual_direction": "NEUTRAL",
        "predicted_price": 0.0,
        "actual_price": 56.62,
        "price_error_pct": null,
        "correct": false
      }
    ],
    "overall_accuracy": 0.0
  },
  {
    "prediction_time": "2026-03-11T14:37:34Z",
    "check_time": "2026-03-11T17:35:01Z",
    "timeframe": "intraday",
    "trigger_type": "scheduled",
    "signal": "BEARISH",
    "signal_correct": false,
    "confidence_at_prediction": 65,
    "ticker_results": [
      {
        "ticker": "QQQ",
        "predicted_direction": "BEARISH",
        "actual_direction": "NEUTRAL",
        "predicted_price": 605.8,
        "actual_price": 608.04,
        "price_error_pct": 0.37,
        "correct": false
      },
      {
        "ticker": "TSLA",
        "predicted_direction": "NEUTRAL",
        "actual_direction": "BEARISH",
        "predicted_price": 410.0,
        "actual_price": 407.65,
        "price_error_pct": 0.573,
        "correct": false
      },
      {
        "ticker": "SPY",
        "predicted_direction": "BEARISH",
        "actual_direction": "NEUTRAL",
        "predicted_price": 674.5,
        "actual_price": 676.14,
        "price_error_pct": 0.243,
        "correct": false
      }
    ],
    "overall_accuracy": 0.0
  },
  {
    "prediction_time": "2026-03-11T18:09:28Z",
    "check_time": "2026-03-11T19:35:02Z",
    "timeframe": "intraday",
    "trigger_type": "scheduled",
    "short_term_signal": "BEARISH",
    "signal": "BEARISH",
    "confidence": 65,
    "confidence_at_prediction": 65,
    "ticker_results": [
      {
        "ticker": "QQQ",
        "price_at_prediction": 606.29,
        "price_at_backcheck": 607.36,
        "actual_move": 1.07,
        "actual_move_pct": 0.1765,
        "actual_direction": "UP",
        "predicted_signal": "BEARISH",
        "directional_correct": false,
        "predicted_price": 603.8,
        "price_error": 3.56,
        "price_error_pct": 0.5896,
        "price_accuracy_grade": "Good"
      },
      {
        "ticker": "SPY",
        "price_at_prediction": 674.481,
        "price_at_backcheck": 675.81,
        "actual_move": 1.329,
        "actual_move_pct": 0.197,
        "actual_direction": "UP",
        "predicted_signal": "BEARISH",
        "directional_correct": false,
        "predicted_price": 671.5,
        "price_error": 4.31,
        "price_error_pct": 0.6418,
        "price_accuracy_grade": "Good"
      },
      {
        "ticker": "NVDA",
        "price_at_prediction": 185.085,
        "price_at_backcheck": 185.485,
        "actual_move": 0.4,
        "actual_move_pct": 0.2161,
        "actual_direction": "UP",
        "predicted_signal": "BEARISH",
        "directional_correct": false,
        "predicted_price": 183.5,
        "price_error": 1.985,
        "price_error_pct": 1.0817,
        "price_accuracy_grade": "Fair"
      },
      {
        "ticker": "IWM",
        "price_at_prediction": 251.395,
        "price_at_backcheck": 252.257,
        "actual_move": 0.862,
        "actual_move_pct": 0.3429,
        "actual_direction": "UP",
        "predicted_signal": "BEARISH",
        "directional_correct": false,
        "predicted_price": 250.2,
        "price_error": 2.057,
        "price_error_pct": 0.8221,
        "price_accuracy_grade": "Good"
      }
    ],
    "overall_directional_accuracy": 0.0,
    "overall_price_error_pct": 0.7838,
    "overall_accuracy": 0.0,
    "signal_correct": false
  },
  {
    "prediction_time": "2026-03-11T17:40:00Z",
    "check_time": "2026-03-11T20:01:01Z",
    "timeframe": "intraday",
    "trigger_type": "scheduled",
    "short_term_signal": "BEARISH",
    "signal": "BEARISH",
    "confidence": 65,
    "confidence_at_prediction": 65,
    "ticker_results": [
      {
        "ticker": "QQQ",
        "price_at_prediction": 606.25,
        "price_at_backcheck": 607.69,
        "actual_move": 1.44,
        "actual_move_pct": 0.2375,
        "actual_direction": "UP",
        "predicted_signal": "BEARISH",
        "directional_correct": false,
        "predicted_price": 604.8,
        "price_error": 2.89,
        "price_error_pct": 0.4778,
        "price_accuracy_grade": "Excellent"
      },
      {
        "ticker": "SPY",
        "price_at_prediction": 674.41,
        "price_at_backcheck": 676.28,
        "actual_move": 1.87,
        "actual_move_pct": 0.2773,
        "actual_direction": "UP",
        "predicted_signal": "BEARISH",
        "directional_correct": false,
        "predicted_price": 672.5,
        "price_error": 3.78,
        "price_error_pct": 0.5621,
        "price_accuracy_grade": "Good"
      },
      {
        "ticker": "IWM",
        "price_at_prediction": 251.29,
        "price_at_backcheck": 252.86,
        "actual_move": 1.57,
        "actual_move_pct": 0.6248,
        "actual_direction": "UP",
        "predicted_signal": "BEARISH",
        "directional_correct": false,
        "predicted_price": 249.5,
        "price_error": 3.36,
        "price_error_pct": 1.3467,
        "price_accuracy_grade": "Fair"
      },
      {
        "ticker": "TSLA",
        "price_at_prediction": 405.65,
        "price_at_backcheck": 407.82,
        "actual_move": 2.17,
        "actual_move_pct": 0.5349,
        "actual_direction": "UP",
        "predicted_signal": "NEUTRAL",
        "directional_correct": false,
        "predicted_price": 406.5,
        "price_error": 1.32,
        "price_error_pct": 0.3247,
        "price_accuracy_grade": "Excellent"
      },
      {
        "ticker": "NVDA",
        "price_at_prediction": 184.84,
        "price_at_backcheck": 185.997,
        "actual_move": 1.157,
        "actual_move_pct": 0.6259,
        "actual_direction": "UP",
        "predicted_signal": "BEARISH",
        "directional_correct": false,
        "predicted_price": 183.9,
        "price_error": 2.097,
        "price_error_pct": 1.1403,
        "price_accuracy_grade": "Fair"
      }
    ],
    "overall_directional_accuracy": 0.0,
    "overall_price_error_pct": 0.7703,
    "overall_accuracy": 0.0,
    "signal_correct": false
  },
  {
    "prediction_time": "2026-03-11T17:30:27Z",
    "check_time": "2026-03-11T20:11:02Z",
    "timeframe": "intraday",
    "trigger_type": "manual",
    "short_term_signal": "BEARISH",
    "signal": "BEARISH",
    "confidence": 65,
    "confidence_at_prediction": 65,
    "ticker_results": [
      {
        "ticker": "QQQ",
        "price_at_prediction": 608.36,
        "price_at_backcheck": 607.69,
        "actual_move": -0.67,
        "actual_move_pct": -0.1101,
        "actual_direction": "DOWN",
        "predicted_signal": "BEARISH",
        "directional_correct": true,
        "predicted_price": 606.5,
        "price_error": 1.19,
        "price_error_pct": 0.1962,
        "price_accuracy_grade": "Excellent"
      },
      {
        "ticker": "SPY",
        "price_at_prediction": 676.53,
        "price_at_backcheck": 676.28,
        "actual_move": -0.25,
        "actual_move_pct": -0.037,
        "actual_direction": "NEUTRAL",
        "predicted_signal": "BEARISH",
        "directional_correct": false,
        "predicted_price": 674.8,
        "price_error": 1.48,
        "price_error_pct": 0.2193,
        "price_accuracy_grade": "Excellent"
      },
      {
        "ticker": "IWM",
        "price_at_prediction": 252.3,
        "price_at_backcheck": 252.86,
        "actual_move": 0.56,
        "actual_move_pct": 0.222,
        "actual_direction": "UP",
        "predicted_signal": "BEARISH",
        "directional_correct": false,
        "predicted_price": 251.2,
        "price_error": 1.66,
        "price_error_pct": 0.6608,
        "price_accuracy_grade": "Good"
      },
      {
        "ticker": "TSLA",
        "price_at_prediction": 408.24,
        "price_at_backcheck": 407.82,
        "actual_move": -0.42,
        "actual_move_pct": -0.1029,
        "actual_direction": "DOWN",
        "predicted_signal": "NEUTRAL",
        "directional_correct": true,
        "predicted_price": 407.5,
        "price_error": 0.32,
        "price_error_pct": 0.0785,
        "price_accuracy_grade": "Excellent"
      },
      {
        "ticker": "NVDA",
        "price_at_prediction": 185.6,
        "price_at_backcheck": 185.997,
        "actual_move": 0.397,
        "actual_move_pct": 0.2139,
        "actual_direction": "UP",
        "predicted_signal": "BEARISH",
        "directional_correct": false,
        "predicted_price": 184.2,
        "price_error": 1.797,
        "price_error_pct": 0.9756,
        "price_accuracy_grade": "Good"
      }
    ],
    "overall_directional_accuracy": 0.4,
    "overall_price_error_pct": 0.4261,
    "overall_accuracy": 0.4,
    "signal_correct": false
  },
  {
    "prediction_time": "2026-03-11T19:40:00Z",
    "check_time": "2026-03-12T13:35:01Z",
    "timeframe": "next_day",
    "trigger_type": "scheduled",
    "short_term_signal": "BEARISH",
    "signal": "BEARISH",
    "confidence": 70,
    "confidence_at_prediction": 70,
    "ticker_results": [
      {
        "ticker": "QQQ",
        "price_at_prediction": 607.39,
        "price_at_backcheck": 603.58,
        "actual_move": -3.81,
        "actual_move_pct": -0.6273,
        "actual_direction": "DOWN",
        "predicted_signal": "BEARISH",
        "directional_correct": true,
        "predicted_price": 602.0,
        "price_error": 1.58,
        "price_error_pct": 0.2625,
        "price_accuracy_grade": "Excellent"
      },
      {
        "ticker": "SPY",
        "price_at_prediction": 675.86,
        "price_at_backcheck": 671.03,
        "actual_move": -4.83,
        "actual_move_pct": -0.7146,
        "actual_direction": "DOWN",
        "predicted_signal": "BEARISH",
        "directional_correct": true,
        "predicted_price": 670.0,
        "price_error": 1.03,
        "price_error_pct": 0.1537,
        "price_accuracy_grade": "Excellent"
      },
      {
        "ticker": "IWM",
        "price_at_prediction": 252.34,
        "price_at_backcheck": 248.3,
        "actual_move": -4.04,
        "actual_move_pct": -1.601,
        "actual_direction": "DOWN",
        "predicted_signal": "BEARISH",
        "directional_correct": true,
        "predicted_price": 249.5,
        "price_error": 1.2,
        "price_error_pct": 0.481,
        "price_accuracy_grade": "Excellent"
      },
      {
        "ticker": "NVDA",
        "price_at_prediction": 185.519,
        "price_at_backcheck": 184.425,
        "actual_move": -1.094,
        "actual_move_pct": -0.5897,
        "actual_direction": "DOWN",
        "predicted_signal": "BEARISH",
        "directional_correct": true,
        "predicted_price": 182.0,
        "price_error": 2.425,
        "price_error_pct": 1.3324,
        "price_accuracy_grade": "Fair"
      }
    ],
    "overall_directional_accuracy": 1.0,
    "overall_price_error_pct": 0.5574,
    "overall_accuracy": 1.0,
    "signal_correct": true
  },
  {
    "prediction_time": "2026-03-11T18:09:28Z",
    "check_time": "2026-03-12T14:38:02Z",
    "timeframe": "next_day",
    "trigger_type": "scheduled",
    "short_term_signal": "BEARISH",
    "signal": "BEARISH",
    "confidence": 70,
    "confidence_at_prediction": 70,
    "ticker_results": [
      {
        "ticker": "QQQ",
        "price_at_prediction": 606.29,
        "price_at_backcheck": 598.24,
        "actual_move": -8.05,
        "actual_move_pct": -1.3277,
        "actual_direction": "DOWN",
        "predicted_signal": "BEARISH",
        "directional_correct": true,
        "predicted_price": 600.5,
        "price_error": 2.26,
        "price_error_pct": 0.3764,
        "price_accuracy_grade": "Excellent"
      },
      {
        "ticker": "SPY",
        "price_at_prediction": 674.481,
        "price_at_backcheck": 667.69,
        "actual_move": -6.791,
        "actual_move_pct": -1.0068,
        "actual_direction": "DOWN",
        "predicted_signal": "BEARISH",
        "directional_correct": true,
        "predicted_price": 668.0,
        "price_error": 0.31,
        "price_error_pct": 0.0464,
        "price_accuracy_grade": "Excellent"
      },
      {
        "ticker": "NVDA",
        "price_at_prediction": 185.085,
        "price_at_backcheck": 182.01,
        "actual_move": -3.075,
        "actual_move_pct": -1.6614,
        "actual_direction": "DOWN",
        "predicted_signal": "BEARISH",
        "directional_correct": true,
        "predicted_price": 181.0,
        "price_error": 1.01,
        "price_error_pct": 0.558,
        "price_accuracy_grade": "Good"
      },
      {
        "ticker": "IWM",
        "price_at_prediction": 251.395,
        "price_at_backcheck": 247.05,
        "actual_move": -4.345,
        "actual_move_pct": -1.7284,
        "actual_direction": "DOWN",
        "predicted_signal": "BEARISH",
        "directional_correct": true,
        "predicted_price": 248.8,
        "price_error": 1.75,
        "price_error_pct": 0.7034,
        "price_accuracy_grade": "Good"
      }
    ],
    "overall_directional_accuracy": 1.0,
    "overall_price_error_pct": 0.4211,
    "overall_accuracy": 1.0,
    "signal_correct": true
  },
  {
    "prediction_time": "2026-03-11T17:40:00Z",
    "check_time": "2026-03-12T14:38:02Z",
    "timeframe": "next_day",
    "trigger_type": "scheduled",
    "short_term_signal": "BEARISH",
    "signal": "BEARISH",
    "confidence": 70,
    "confidence_at_prediction": 70,
    "ticker_results": [
      {
        "ticker": "QQQ",
        "price_at_prediction": 606.25,
        "price_at_backcheck": 598.19,
        "actual_move": -8.06,
        "actual_move_pct": -1.3295,
        "actual_direction": "DOWN",
        "predicted_signal": "BEARISH",
        "directional_correct": true,
        "predicted_price": 601.5,
        "price_error": 3.31,
        "price_error_pct": 0.5503,
        "price_accuracy_grade": "Good"
      },
      {
        "ticker": "SPY",
        "price_at_prediction": 674.41,
        "price_at_backcheck": 667.68,
        "actual_move": -6.73,
        "actual_move_pct": -0.9979,
        "actual_direction": "DOWN",
        "predicted_signal": "BEARISH",
        "directional_correct": true,
        "predicted_price": 668.25,
        "price_error": 0.57,
        "price_error_pct": 0.0853,
        "price_accuracy_grade": "Excellent"
      },
      {
        "ticker": "IWM",
        "price_at_prediction": 251.29,
        "price_at_backcheck": 247.02,
        "actual_move": -4.27,
        "actual_move_pct": -1.6992,
        "actual_direction": "DOWN",
        "predicted_signal": "BEARISH",
        "directional_correct": true,
        "predicted_price": 247.0,
        "price_error": 0.02,
        "price_error_pct": 0.0081,
        "price_accuracy_grade": "Excellent"
      },
      {
        "ticker": "TSLA",
        "price_at_prediction": 405.65,
        "price_at_backcheck": 396.735,
        "actual_move": -8.915,
        "actual_move_pct": -2.1977,
        "actual_direction": "DOWN",
        "predicted_signal": "BEARISH",
        "directional_correct": true,
        "predicted_price": 398.0,
        "price_error": 1.265,
        "price_error_pct": 0.3178,
        "price_accuracy_grade": "Excellent"
      },
      {
        "ticker": "NVDA",
        "price_at_prediction": 184.84,
        "price_at_backcheck": 181.98,
        "actual_move": -2.86,
        "actual_move_pct": -1.5473,
        "actual_direction": "DOWN",
        "predicted_signal": "BEARISH",
        "directional_correct": true,
        "predicted_price": 181.5,
        "price_error": 0.48,
        "price_error_pct": 0.2645,
        "price_accuracy_grade": "Excellent"
      }
    ],
    "overall_directional_accuracy": 1.0,
    "overall_price_error_pct": 0.2452,
    "overall_accuracy": 1.0,
    "signal_correct": true
  },
  {
    "prediction_time": "2026-03-11T17:30:27Z",
    "check_time": "2026-03-12T14:38:02Z",
    "timeframe": "next_day",
    "trigger_type": "scheduled",
    "short_term_signal": "BEARISH",
    "signal": "BEARISH",
    "confidence": 70,
    "confidence_at_prediction": 70,
    "ticker_results": [
      {
        "ticker": "QQQ",
        "price_at_prediction": 608.36,
        "price_at_backcheck": 598.17,
        "actual_move": -10.19,
        "actual_move_pct": -1.675,
        "actual_direction": "DOWN",
        "predicted_signal": "BEARISH",
        "directional_correct": true,
        "predicted_price": 604.0,
        "price_error": 5.83,
        "price_error_pct": 0.9652,
        "price_accuracy_grade": "Good"
      },
      {
        "ticker": "SPY",
        "price_at_prediction": 676.53,
        "price_at_backcheck": 667.8,
        "actual_move": -8.73,
        "actual_move_pct": -1.2904,
        "actual_direction": "DOWN",
        "predicted_signal": "BEARISH",
        "directional_correct": true,
        "predicted_price": 672.0,
        "price_error": 4.2,
        "price_error_pct": 0.625,
        "price_accuracy_grade": "Good"
      },
      {
        "ticker": "IWM",
        "price_at_prediction": 252.3,
        "price_at_backcheck": 247.03,
        "actual_move": -5.27,
        "actual_move_pct": -2.0888,
        "actual_direction": "DOWN",
        "predicted_signal": "BEARISH",
        "directional_correct": true,
        "predicted_price": 248.5,
        "price_error": 1.47,
        "price_error_pct": 0.5915,
        "price_accuracy_grade": "Good"
      },
      {
        "ticker": "TSLA",
        "price_at_prediction": 408.24,
        "price_at_backcheck": 396.575,
        "actual_move": -11.665,
        "actual_move_pct": -2.8574,
        "actual_direction": "DOWN",
        "predicted_signal": "BEARISH",
        "directional_correct": true,
        "predicted_price": 402.0,
        "price_error": 5.425,
        "price_error_pct": 1.3495,
        "price_accuracy_grade": "Fair"
      },
      {
        "ticker": "NVDA",
        "price_at_prediction": 185.6,
        "price_at_backcheck": 182.0,
        "actual_move": -3.6,
        "actual_move_pct": -1.9397,
        "actual_direction": "DOWN",
        "predicted_signal": "BEARISH",
        "directional_correct": true,
        "predicted_price": 183.5,
        "price_error": 1.5,
        "price_error_pct": 0.8174,
        "price_accuracy_grade": "Good"
      }
    ],
    "overall_directional_accuracy": 1.0,
    "overall_price_error_pct": 0.8697,
    "overall_accuracy": 1.0,
    "signal_correct": true
  },
  {
    "prediction_time": "2026-03-11T17:16:29Z",
    "check_time": "2026-03-12T14:38:02Z",
    "timeframe": "next_day",
    "trigger_type": "scheduled",
    "short_term_signal": "BEARISH",
    "signal": "BEARISH",
    "confidence": 80,
    "confidence_at_prediction": 80,
    "ticker_results": [
      {
        "ticker": "QQQ",
        "price_at_prediction": 608.16,
        "price_at_backcheck": 598.17,
        "actual_move": -9.99,
        "actual_move_pct": -1.6427,
        "actual_direction": "DOWN",
        "predicted_signal": "BEARISH",
        "directional_correct": true,
        "predicted_price": 603.5,
        "price_error": 5.33,
        "price_error_pct": 0.8832,
        "price_accuracy_grade": "Good"
      },
      {
        "ticker": "SPY",
        "price_at_prediction": 675.96,
        "price_at_backcheck": 667.62,
        "actual_move": -8.34,
        "actual_move_pct": -1.2338,
        "actual_direction": "DOWN",
        "predicted_signal": "BEARISH",
        "directional_correct": true,
        "predicted_price": 671.0,
        "price_error": 3.38,
        "price_error_pct": 0.5037,
        "price_accuracy_grade": "Good"
      },
      {
        "ticker": "IWM",
        "price_at_prediction": 251.99,
        "price_at_backcheck": 246.992,
        "actual_move": -4.998,
        "actual_move_pct": -1.9834,
        "actual_direction": "DOWN",
        "predicted_signal": "BEARISH",
        "directional_correct": true,
        "predicted_price": 248.0,
        "price_error": 1.008,
        "price_error_pct": 0.4065,
        "price_accuracy_grade": "Excellent"
      },
      {
        "ticker": "NVDA",
        "price_at_prediction": 185.67,
        "price_at_backcheck": 181.975,
        "actual_move": -3.695,
        "actual_move_pct": -1.9901,
        "actual_direction": "DOWN",
        "predicted_signal": "BEARISH",
        "directional_correct": true,
        "predicted_price": 182.0,
        "price_error": 0.025,
        "price_error_pct": 0.0137,
        "price_accuracy_grade": "Excellent"
      }
    ],
    "overall_directional_accuracy": 1.0,
    "overall_price_error_pct": 0.4518,
    "overall_accuracy": 1.0,
    "signal_correct": true
  },
  {
    "prediction_time": "2026-03-11T17:06:26Z",
    "check_time": "2026-03-12T14:38:02Z",
    "timeframe": "next_day",
    "trigger_type": "scheduled",
    "short_term_signal": "BEARISH",
    "signal": "BEARISH",
    "confidence": 70,
    "confidence_at_prediction": 70,
    "ticker_results": [
      {
        "ticker": "QQQ",
        "price_at_prediction": 608.52,
        "price_at_backcheck": 598.17,
        "actual_move": -10.35,
        "actual_move_pct": -1.7008,
        "actual_direction": "DOWN",
        "predicted_signal": "BEARISH",
        "directional_correct": true,
        "predicted_price": 602.0,
        "price_error": 3.83,
        "price_error_pct": 0.6362,
        "price_accuracy_grade": "Good"
      },
      {
        "ticker": "SPY",
        "price_at_prediction": 676.4,
        "price_at_backcheck": 667.54,
        "actual_move": -8.86,
        "actual_move_pct": -1.3099,
        "actual_direction": "DOWN",
        "predicted_signal": "BEARISH",
        "directional_correct": true,
        "predicted_price": 670.0,
        "price_error": 2.46,
        "price_error_pct": 0.3672,
        "price_accuracy_grade": "Excellent"
      },
      {
        "ticker": "NVDA",
        "price_at_prediction": 185.71,
        "price_at_backcheck": 181.96,
        "actual_move": -3.75,
        "actual_move_pct": -2.0193,
        "actual_direction": "DOWN",
        "predicted_signal": "BEARISH",
        "directional_correct": true,
        "predicted_price": 182.0,
        "price_error": 0.04,
        "price_error_pct": 0.022,
        "price_accuracy_grade": "Excellent"
      },
      {
        "ticker": "IWM",
        "price_at_prediction": 252.44,
        "price_at_backcheck": 247.0,
        "actual_move": -5.44,
        "actual_move_pct": -2.155,
        "actual_direction": "DOWN",
        "predicted_signal": "BEARISH",
        "directional_correct": true,
        "predicted_price": 248.5,
        "price_error": 1.5,
        "price_error_pct": 0.6036,
        "price_accuracy_grade": "Good"
      }
    ],
    "overall_directional_accuracy": 1.0,
    "overall_price_error_pct": 0.4073,
    "overall_accuracy": 1.0,
    "signal_correct": true
  },
  {
    "prediction_time": "2026-03-11T15:40:00Z",
    "check_time": "2026-03-12T14:38:02Z",
    "timeframe": "next_day",
    "trigger_type": "scheduled",
    "short_term_signal": "BEARISH",
    "signal": "BEARISH",
    "confidence": 70,
    "confidence_at_prediction": 70,
    "ticker_results": [
      {
        "ticker": "QQQ",
        "price_at_prediction": 606.84,
        "price_at_backcheck": 598.051,
        "actual_move": -8.789,
        "actual_move_pct": -1.4483,
        "actual_direction": "DOWN",
        "predicted_signal": "BEARISH",
        "directional_correct": true,
        "predicted_price": 600.5,
        "price_error": 2.449,
        "price_error_pct": 0.4078,
        "price_accuracy_grade": "Excellent"
      },
      {
        "ticker": "SPY",
        "price_at_prediction": 674.85,
        "price_at_backcheck": 667.54,
        "actual_move": -7.31,
        "actual_move_pct": -1.0832,
        "actual_direction": "DOWN",
        "predicted_signal": "BEARISH",
        "directional_correct": true,
        "predicted_price": 668.0,
        "price_error": 0.46,
        "price_error_pct": 0.0689,
        "price_accuracy_grade": "Excellent"
      },
      {
        "ticker": "IWM",
        "price_at_prediction": 251.6,
        "price_at_backcheck": 247.0,
        "actual_move": -4.6,
        "actual_move_pct": -1.8283,
        "actual_direction": "DOWN",
        "predicted_signal": "BEARISH",
        "directional_correct": true,
        "predicted_price": 247.8,
        "price_error": 0.8,
        "price_error_pct": 0.3228,
        "price_accuracy_grade": "Excellent"
      },
      {
        "ticker": "TSLA",
        "price_at_prediction": 407.3,
        "price_at_backcheck": 396.585,
        "actual_move": -10.715,
        "actual_move_pct": -2.6307,
        "actual_direction": "DOWN",
        "predicted_signal": "BEARISH",
        "directional_correct": true,
        "predicted_price": 395.0,
        "price_error": 1.585,
        "price_error_pct": 0.4013,
        "price_accuracy_grade": "Excellent"
      },
      {
        "ticker": "XLE",
        "price_at_prediction": null,
        "price_at_backcheck": 57.69,
        "actual_move": null,
        "actual_move_pct": null,
        "actual_direction": "NEUTRAL",
        "predicted_signal": "BULLISH",
        "directional_correct": false,
        "predicted_price": 0.0,
        "price_error": null,
        "price_error_pct": null,
        "price_accuracy_grade": null
      }
    ],
    "overall_directional_accuracy": 0.8,
    "overall_price_error_pct": 0.3002,
    "overall_accuracy": 0.8,
    "signal_correct": true
  },
  {
    "prediction_time": "2026-03-11T14:37:34Z",
    "check_time": "2026-03-12T14:38:02Z",
    "timeframe": "next_day",
    "trigger_type": "scheduled",
    "short_term_signal": "BEARISH",
    "signal": "BEARISH",
    "confidence": 70,
    "confidence_at_prediction": 70,
    "ticker_results": [
      {
        "ticker": "QQQ",
        "price_at_prediction": 608.47,
        "price_at_backcheck": 598.09,
        "actual_move": -10.38,
        "actual_move_pct": -1.7059,
        "actual_direction": "DOWN",
        "predicted_signal": "BEARISH",
        "directional_correct": true,
        "predicted_price": 598.5,
        "price_error": 0.41,
        "price_error_pct": 0.0685,
        "price_accuracy_grade": "Excellent"
      },
      {
        "ticker": "TSLA",
        "price_at_prediction": 412.3,
        "price_at_backcheck": 396.6,
        "actual_move": -15.7,
        "actual_move_pct": -3.8079,
        "actual_direction": "DOWN",
        "predicted_signal": "BEARISH",
        "directional_correct": true,
        "predicted_price": 395.0,
        "price_error": 1.6,
        "price_error_pct": 0.4051,
        "price_accuracy_grade": "Excellent"
      },
      {
        "ticker": "SPY",
        "price_at_prediction": 676.7,
        "price_at_backcheck": 667.53,
        "actual_move": -9.17,
        "actual_move_pct": -1.3551,
        "actual_direction": "DOWN",
        "predicted_signal": "BEARISH",
        "directional_correct": true,
        "predicted_price": 668.0,
        "price_error": 0.47,
        "price_error_pct": 0.0704,
        "price_accuracy_grade": "Excellent"
      }
    ],
    "overall_directional_accuracy": 1.0,
    "overall_price_error_pct": 0.1813,
    "overall_accuracy": 1.0,
    "signal_correct": true
  },
  {
    "prediction_time": "2026-03-11T13:40:01Z",
    "check_time": "2026-03-12T14:38:02Z",
    "timeframe": "next_day",
    "trigger_type": "scheduled",
    "short_term_signal": "BEARISH",
    "signal": "BEARISH",
    "confidence": 80,
    "confidence_at_prediction": 80,
    "ticker_results": [
      {
        "ticker": "QQQ",
        "price_at_prediction": 610.55,
        "price_at_backcheck": 598.09,
        "actual_move": -12.46,
        "actual_move_pct": -2.0408,
        "actual_direction": "DOWN",
        "predicted_signal": "BEARISH",
        "directional_correct": true,
        "predicted_price": 603.0,
        "price_error": 4.91,
        "price_error_pct": 0.8143,
        "price_accuracy_grade": "Good"
      },
      {
        "ticker": "SPY",
        "price_at_prediction": 678.4,
        "price_at_backcheck": 667.541,
        "actual_move": -10.859,
        "actual_move_pct": -1.6007,
        "actual_direction": "DOWN",
        "predicted_signal": "BEARISH",
        "directional_correct": true,
        "predicted_price": 672.0,
        "price_error": 4.459,
        "price_error_pct": 0.6635,
        "price_accuracy_grade": "Good"
      },
      {
        "ticker": "TSLA",
        "price_at_prediction": 408.77,
        "price_at_backcheck": 396.55,
        "actual_move": -12.22,
        "actual_move_pct": -2.9895,
        "actual_direction": "DOWN",
        "predicted_signal": "BEARISH",
        "directional_correct": true,
        "predicted_price": 398.0,
        "price_error": 1.45,
        "price_error_pct": 0.3643,
        "price_accuracy_grade": "Excellent"
      },
      {
        "ticker": "IWM",
        "price_at_prediction": 252.14,
        "price_at_backcheck": 247.02,
        "actual_move": -5.12,
        "actual_move_pct": -2.0306,
        "actual_direction": "DOWN",
        "predicted_signal": "BEARISH",
        "directional_correct": true,
        "predicted_price": 248.5,
        "price_error": 1.48,
        "price_error_pct": 0.5956,
        "price_accuracy_grade": "Good"
      },
      {
        "ticker": "NVDA",
        "price_at_prediction": 186.06,
        "price_at_backcheck": 181.95,
        "actual_move": -4.11,
        "actual_move_pct": -2.209,
        "actual_direction": "DOWN",
        "predicted_signal": "BEARISH",
        "directional_correct": true,
        "predicted_price": 182.0,
        "price_error": 0.05,
        "price_error_pct": 0.0275,
        "price_accuracy_grade": "Excellent"
      }
    ],
    "overall_directional_accuracy": 1.0,
    "overall_price_error_pct": 0.493,
    "overall_accuracy": 1.0,
    "signal_correct": true
  },
  {
    "prediction_time": "2026-03-11T13:37:56Z",
    "check_time": "2026-03-12T14:38:02Z",
    "timeframe": "next_day",
    "trigger_type": "scheduled",
    "short_term_signal": "BEARISH",
    "signal": "BEARISH",
    "confidence": 80,
    "confidence_at_prediction": 80,
    "ticker_results": [
      {
        "ticker": "QQQ",
        "price_at_prediction": 610.45,
        "price_at_backcheck": 598.09,
        "actual_move": -12.36,
        "actual_move_pct": -2.0247,
        "actual_direction": "DOWN",
        "predicted_signal": "BEARISH",
        "directional_correct": true,
        "predicted_price": 598.5,
        "price_error": 0.41,
        "price_error_pct": 0.0685,
        "price_accuracy_grade": "Excellent"
      },
      {
        "ticker": "SPY",
        "price_at_prediction": 677.97,
        "price_at_backcheck": 667.58,
        "actual_move": -10.39,
        "actual_move_pct": -1.5325,
        "actual_direction": "DOWN",
        "predicted_signal": "BEARISH",
        "directional_correct": true,
        "predicted_price": 670.0,
        "price_error": 2.42,
        "price_error_pct": 0.3612,
        "price_accuracy_grade": "Excellent"
      },
      {
        "ticker": "TSLA",
        "price_at_prediction": 409.57,
        "price_at_backcheck": 396.56,
        "actual_move": -13.01,
        "actual_move_pct": -3.1765,
        "actual_direction": "DOWN",
        "predicted_signal": "BEARISH",
        "directional_correct": true,
        "predicted_price": 395.0,
        "price_error": 1.56,
        "price_error_pct": 0.3949,
        "price_accuracy_grade": "Excellent"
      },
      {
        "ticker": "IWM",
        "price_at_prediction": 251.5,
        "price_at_backcheck": 247.05,
        "actual_move": -4.45,
        "actual_move_pct": -1.7694,
        "actual_direction": "DOWN",
        "predicted_signal": "BEARISH",
        "directional_correct": true,
        "predicted_price": 245.0,
        "price_error": 2.05,
        "price_error_pct": 0.8367,
        "price_accuracy_grade": "Good"
      },
      {
        "ticker": "NVDA",
        "price_at_prediction": 185.57,
        "price_at_backcheck": 182.05,
        "actual_move": -3.52,
        "actual_move_pct": -1.8969,
        "actual_direction": "DOWN",
        "predicted_signal": "BEARISH",
        "directional_correct": true,
        "predicted_price": 178.0,
        "price_error": 4.05,
        "price_error_pct": 2.2753,
        "price_accuracy_grade": "Poor"
      }
    ],
    "overall_directional_accuracy": 1.0,
    "overall_price_error_pct": 0.7873,
    "overall_accuracy": 1.0,
    "signal_correct": true
  },
  {
    "prediction_time": "2026-03-11T03:50:13Z",
    "check_time": "2026-03-12T14:38:02Z",
    "timeframe": "next_day",
    "trigger_type": "scheduled",
    "short_term_signal": "BEARISH",
    "signal": "BEARISH",
    "confidence": 80,
    "confidence_at_prediction": 80,
    "ticker_results": [
      {
        "ticker": "QQQ",
        "price_at_prediction": 607.77,
        "price_at_backcheck": 598.051,
        "actual_move": -9.719,
        "actual_move_pct": -1.5991,
        "actual_direction": "DOWN",
        "predicted_signal": "BEARISH",
        "directional_correct": true,
        "predicted_price": 602.0,
        "price_error": 3.949,
        "price_error_pct": 0.656,
        "price_accuracy_grade": "Good"
      },
      {
        "ticker": "IWM",
        "price_at_prediction": 253.36,
        "price_at_backcheck": 246.99,
        "actual_move": -6.37,
        "actual_move_pct": -2.5142,
        "actual_direction": "DOWN",
        "predicted_signal": "BEARISH",
        "directional_correct": true,
        "predicted_price": 248.0,
        "price_error": 1.01,
        "price_error_pct": 0.4073,
        "price_accuracy_grade": "Excellent"
      },
      {
        "ticker": "NVDA",
        "price_at_prediction": 184.77,
        "price_at_backcheck": 181.94,
        "actual_move": -2.83,
        "actual_move_pct": -1.5316,
        "actual_direction": "DOWN",
        "predicted_signal": "BEARISH",
        "directional_correct": true,
        "predicted_price": 180.0,
        "price_error": 1.94,
        "price_error_pct": 1.0778,
        "price_accuracy_grade": "Fair"
      },
      {
        "ticker": "SPY",
        "price_at_prediction": 677.18,
        "price_at_backcheck": 667.54,
        "actual_move": -9.64,
        "actual_move_pct": -1.4236,
        "actual_direction": "DOWN",
        "predicted_signal": "BEARISH",
        "directional_correct": true,
        "predicted_price": 670.0,
        "price_error": 2.46,
        "price_error_pct": 0.3672,
        "price_accuracy_grade": "Excellent"
      }
    ],
    "overall_directional_accuracy": 1.0,
    "overall_price_error_pct": 0.6271,
    "overall_accuracy": 1.0,
    "signal_correct": true
  },
  {
    "prediction_time": "2026-03-12T14:14:27Z",
    "check_time": "2026-03-12T15:35:00Z",
    "timeframe": "intraday",
    "trigger_type": "scheduled",
    "short_term_signal": "BULLISH",
    "signal": "BULLISH",
    "confidence": 45,
    "confidence_at_prediction": 45,
    "ticker_results": [
      {
        "ticker": "QQQ",
        "price_at_prediction": 601.59,
        "price_at_backcheck": 598.72,
        "actual_move": -2.87,
        "actual_move_pct": -0.4771,
        "actual_direction": "DOWN",
        "predicted_signal": "BULLISH",
        "directional_correct": false,
        "predicted_price": 603.2,
        "price_error": 4.48,
        "price_error_pct": 0.7427,
        "price_accuracy_grade": "Good"
      },
      {
        "ticker": "SPY",
        "price_at_prediction": 670.86,
        "price_at_backcheck": 667.91,
        "actual_move": -2.95,
        "actual_move_pct": -0.4397,
        "actual_direction": "DOWN",
        "predicted_signal": "BULLISH",
        "directional_correct": false,
        "predicted_price": 672.5,
        "price_error": 4.59,
        "price_error_pct": 0.6825,
        "price_accuracy_grade": "Good"
      },
      {
        "ticker": "NVDA",
        "price_at_prediction": 182.94,
        "price_at_backcheck": 182.999,
        "actual_move": 0.059,
        "actual_move_pct": 0.0323,
        "actual_direction": "NEUTRAL",
        "predicted_signal": "BULLISH",
        "directional_correct": false,
        "predicted_price": 184.5,
        "price_error": 1.501,
        "price_error_pct": 0.8136,
        "price_accuracy_grade": "Good"
      },
      {
        "ticker": "XLE",
        "price_at_prediction": null,
        "price_at_backcheck": 57.99,
        "actual_move": null,
        "actual_move_pct": null,
        "actual_direction": "NEUTRAL",
        "predicted_signal": "BULLISH",
        "directional_correct": false,
        "predicted_price": 102.5,
        "price_error": 44.51,
        "price_error_pct": 43.4244,
        "price_accuracy_grade": "Poor"
      },
      {
        "ticker": "META",
        "price_at_prediction": 646.595,
        "price_at_backcheck": 640.42,
        "actual_move": -6.175,
        "actual_move_pct": -0.955,
        "actual_direction": "DOWN",
        "predicted_signal": "BEARISH",
        "directional_correct": true,
        "predicted_price": 644.0,
        "price_error": 3.58,
        "price_error_pct": 0.5559,
        "price_accuracy_grade": "Good"
      }
    ],
    "overall_directional_accuracy": 0.2,
    "overall_price_error_pct": 9.2438,
    "overall_accuracy": 0.2,
    "signal_correct": false
  },
  {
    "prediction_time": "2026-03-12T14:42:28Z",
    "check_time": "2026-03-12T16:16:00Z",
    "timeframe": "intraday",
    "trigger_type": "manual",
    "short_term_signal": "BEARISH",
    "signal": "BEARISH",
    "confidence": 45,
    "confidence_at_prediction": 45,
    "ticker_results": [
      {
        "ticker": "QQQ",
        "price_at_prediction": 598.495,
        "price_at_backcheck": 600.46,
        "actual_move": 1.965,
        "actual_move_pct": 0.3283,
        "actual_direction": "UP",
        "predicted_signal": "BEARISH",
        "directional_correct": false,
        "predicted_price": 596.8,
        "price_error": 3.66,
        "price_error_pct": 0.6133,
        "price_accuracy_grade": "Good"
      },
      {
        "ticker": "SPY",
        "price_at_prediction": 667.79,
        "price_at_backcheck": 669.38,
        "actual_move": 1.59,
        "actual_move_pct": 0.2381,
        "actual_direction": "UP",
        "predicted_signal": "BEARISH",
        "directional_correct": false,
        "predicted_price": 665.5,
        "price_error": 3.88,
        "price_error_pct": 0.583,
        "price_accuracy_grade": "Good"
      },
      {
        "ticker": "NVDA",
        "price_at_prediction": 181.885,
        "price_at_backcheck": 184.77,
        "actual_move": 2.885,
        "actual_move_pct": 1.5862,
        "actual_direction": "UP",
        "predicted_signal": "BEARISH",
        "directional_correct": false,
        "predicted_price": 180.5,
        "price_error": 4.27,
        "price_error_pct": 2.3657,
        "price_accuracy_grade": "Poor"
      },
      {
        "ticker": "IWM",
        "price_at_prediction": 247.21,
        "price_at_backcheck": 248.6,
        "actual_move": 1.39,
        "actual_move_pct": 0.5623,
        "actual_direction": "UP",
        "predicted_signal": "BEARISH",
        "directional_correct": false,
        "predicted_price": 245.9,
        "price_error": 2.7,
        "price_error_pct": 1.098,
        "price_accuracy_grade": "Fair"
      },
      {
        "ticker": "AAPL",
        "price_at_prediction": 254.82,
        "price_at_backcheck": 255.871,
        "actual_move": 1.051,
        "actual_move_pct": 0.4124,
        "actual_direction": "UP",
        "predicted_signal": "BEARISH",
        "directional_correct": false,
        "predicted_price": 253.2,
        "price_error": 2.671,
        "price_error_pct": 1.0549,
        "price_accuracy_grade": "Fair"
      }
    ],
    "overall_directional_accuracy": 0.0,
    "overall_price_error_pct": 1.143,
    "overall_accuracy": 0.0,
    "signal_correct": false
  },
  {
    "prediction_time": "2026-03-12T15:16:26Z",
    "check_time": "2026-03-12T16:44:02Z",
    "timeframe": "intraday",
    "trigger_type": "manual",
    "short_term_signal": "BULLISH",
    "signal": "BULLISH",
    "confidence": 45,
    "confidence_at_prediction": 45,
    "ticker_results": [
      {
        "ticker": "QQQ",
        "price_at_prediction": 598.045,
        "price_at_backcheck": 600.66,
        "actual_move": 2.615,
        "actual_move_pct": 0.4373,
        "actual_direction": "UP",
        "predicted_signal": "BULLISH",
        "directional_correct": true,
        "predicted_price": 600.25,
        "price_error": 0.41,
        "price_error_pct": 0.0683,
        "price_accuracy_grade": "Excellent"
      },
      {
        "ticker": "SPY",
        "price_at_prediction": 667.25,
        "price_at_backcheck": 669.68,
        "actual_move": 2.43,
        "actual_move_pct": 0.3642,
        "actual_direction": "UP",
        "predicted_signal": "BULLISH",
        "directional_correct": true,
        "predicted_price": 669.5,
        "price_error": 0.18,
        "price_error_pct": 0.0269,
        "price_accuracy_grade": "Excellent"
      },
      {
        "ticker": "NVDA",
        "price_at_prediction": 182.27,
        "price_at_backcheck": 184.52,
        "actual_move": 2.25,
        "actual_move_pct": 1.2344,
        "actual_direction": "UP",
        "predicted_signal": "BULLISH",
        "directional_correct": true,
        "predicted_price": 183.75,
        "price_error": 0.77,
        "price_error_pct": 0.419,
        "price_accuracy_grade": "Excellent"
      },
      {
        "ticker": "XLE",
        "price_at_prediction": null,
        "price_at_backcheck": 58.01,
        "actual_move": null,
        "actual_move_pct": null,
        "actual_direction": "NEUTRAL",
        "predicted_signal": "BULLISH",
        "directional_correct": false,
        "predicted_price": 0.0,
        "price_error": null,
        "price_error_pct": null,
        "price_accuracy_grade": null
      },
      {
        "ticker": "IWM",
        "price_at_prediction": 246.85,
        "price_at_backcheck": 249.06,
        "actual_move": 2.21,
        "actual_move_pct": 0.8953,
        "actual_direction": "UP",
        "predicted_signal": "NEUTRAL",
        "directional_correct": false,
        "predicted_price": 248.1,
        "price_error": 0.96,
        "price_error_pct": 0.3869,
        "price_accuracy_grade": "Excellent"
      }
    ],
    "overall_directional_accuracy": 0.6,
    "overall_price_error_pct": 0.2253,
    "overall_accuracy": 0.6,
    "signal_correct": true
  }
]